<?xml version="1.0" encoding="utf-8"?>
<law>
    <structure>
        <unit label="part" identifier="3" order_by="3" level="1">Courts, Judicial Officers And Proceedings In Civil Cases</unit>
        <unit label="title" identifier="2" order_by="2" level="2">Actions And Proceedings Therein</unit>
        <unit label="chapter" identifier="223" order_by="223" level="3">Commencement Of Actions, Service Of Process</unit>
    </structure>
    <section_number>49</section_number>
    <catch_line>Attached Personalty; Keeping On Owner’S Premises</catch_line>
    <order_by>49</order_by>
    <text>
        Personal property which has been attached may, subject to the preceding section, be kept on the premises where it is found, unless the owner or occupant of the premises in writing requests the officer to remove his keeper therefrom; and if the defendant in writing requests the officer to allow property which has been attached on the premises of the defendant to remain there until he may give bond to dissolve the attachment, the property shall not be removed until he has had reasonable opportunity to give such bond.
    </text>
</law>