<?xml version="1.0" encoding="utf-8"?>
<law>
    <structure>
        <unit label="part" identifier="3" order_by="3" level="1">Courts, Judicial Officers And Proceedings In Civil Cases</unit>
        <unit label="title" identifier="2" order_by="2" level="2">Actions And Proceedings Therein</unit>
        <unit label="chapter" identifier="233" order_by="233" level="3">Witnesses And Evidence</unit>
    </structure>
    <section_number>62</section_number>
    <catch_line>Recording Deposition</catch_line>
    <order_by>62</order_by>
    <text>
        After such deposition has been taken, it shall be returned to the court by whose order the commission issued, which, if the deposition is found to have been taken according to law and the directions contained in the commission, shall order it to be recorded within thirty days after the date of the order in the registry of deeds, in the manner provided in section fifty.
    </text>
</law>