<?xml version="1.0" encoding="utf-8"?>
<law>
    <structure>
        <unit label="part" identifier="3" order_by="3" level="1">Courts, Judicial Officers And Proceedings In Civil Cases</unit>
        <unit label="title" identifier="2" order_by="2" level="2">Actions And Proceedings Therein</unit>
        <unit label="chapter" identifier="233" order_by="233" level="3">Witnesses And Evidence</unit>
    </structure>
    <section_number>5</section_number>
    <catch_line>Penalty For Nonattendance; Contempt</catch_line>
    <order_by>5</order_by>
    <text>
        Such failure to attend as a witness before a court, justice of the peace, master in chancery, master or auditor appointed by a court, or the county commissioners, shall also be a contempt of the court, and may be punished, in case of such failure to attend as a witness in a criminal prosecution, by a fine of not more than two hundred dollars or by imprisonment for not more than one month or both, or, in case of any other such failure to attend as aforesaid, by a fine of not more than twenty dollars.
    </text>
</law>