<?xml version="1.0" encoding="utf-8"?>
<law>
    <structure>
        <unit label="part" identifier="1" order_by="1" level="1">Administration Of The Government</unit>
        <unit label="title" identifier="4" order_by="4" level="2">Civil Service, Retirements And Pensions</unit>
        <unit label="chapter" identifier="32B" order_by="32B" level="3">Contributory Group General Or Blanket Insurance For Persons In The Service Of Counties, Cities, Towns And Districts, And Their Dependents</unit>
    </structure>
    <section_number>24</section_number>
    <catch_line>Health Care Flexible Spending Accounts</catch_line>
    <order_by>24</order_by>
    <text>
        [ Text of section added by 2011, 69, Sec. 3 effective July 12, 2011.]  An appropriate public authority of a political subdivision which has undertaken to provide health insurance coverage to its subscribers under this chapter may provide health care flexible spending accounts to allow certain subscribers, as determined by the appropriate public authority, to set aside a portion of earnings to pay for qualified expenses which may include, but shall not be limited to, out-of-pocket costs such as inpatient and outpatient copayments, calendar year deductibles, office visit copayments and prescription drug copayments.
    </text>
</law>