<?xml version="1.0" encoding="utf-8"?>
<law>
    <structure>
        <unit label="part" identifier="1" order_by="1" level="1">Administration Of The Government</unit>
        <unit label="title" identifier="15" order_by="15" level="2">Regulation Of Trade</unit>
        <unit label="chapter" identifier="94" order_by="94" level="3">Inspection And Sale Of Food, Drugs And Various Articles</unit>
    </structure>
    <section_number>314</section_number>
    <catch_line>Definitions Applicable To Secs. 315 To 318</catch_line>
    <order_by>314</order_by>
    <text>
        As used in sections three hundred and fifteen through three hundred and eighteen, inclusive, the following words and phrases shall, unless the context otherwise requires, have the following meanings:— 
“Appliance”, an air conditioner, refrigerator, freezer or refrigerator-freezer which is not used or secondhand; 
“Class of appliances”, all appliances performing similar functions; 
“Consumer”, a person who purchases an appliance for use by himself or others and not for resale as a new appliance; 
“Deputy director”, the deputy director of standards; 
“Director”, the director of consumer affairs and business regulation; 
“Subclass of appliances”, those appliances within a class of appliances which are determined by the secretary to be comparable in size, capacity or capability.
    </text>
</law>