<?xml version="1.0" encoding="utf-8"?>
<law>
    <structure>
        <unit label="part" identifier="1" order_by="1" level="1">Administration Of The Government</unit>
        <unit label="title" identifier="7" order_by="7" level="2">Cities, Towns And Districts</unit>
        <unit label="chapter" identifier="40A" order_by="40A" level="3">Zoning</unit>
    </structure>
    <section_number>4</section_number>
    <catch_line>Uniform Districts</catch_line>
    <order_by>4</order_by>
    <text>
        Any zoning ordinance or by-law which divides cities and towns into districts shall be uniform within the district for each class or kind of structures or uses permitted. 
Districts shall be shown on a zoning map in a manner sufficient for identification. Such maps shall be part of zoning ordinances or by-laws. Assessors’ or property plans may be used as the basis for zoning maps. If more than four sheets or plates are used for a zoning map, an index map showing districts in outline shall be part of the zoning map and of the zoning ordinance or by-law.
    </text>
</law>