<?xml version="1.0" encoding="utf-8"?>
<law>
    <structure>
        <unit label="part" identifier="1" order_by="1" level="1">Administration Of The Government</unit>
        <unit label="title" identifier="2" order_by="2" level="2">Executive And Administrative Officers Of The Commonwealth</unit>
        <unit label="chapter" identifier="12" order_by="12" level="3">Department Of The Attorney General, And The District Attorneys</unit>
    </structure>
    <section_number>11H</section_number>
    <catch_line>Violations Of Constitutional Rights; Civil Actions By Attorney General; Venue</catch_line>
    <order_by>11H</order_by>
    <text>
        Whenever any person or persons, whether or not acting under color of law, interfere by threats, intimidation or coercion, or attempt to interfere by threats, intimidation or coercion, with the exercise or enjoyment by any other person or persons of rights secured by the constitution or laws of the United States, or of rights secured by the constitution or laws of the commonwealth, the attorney general may bring a civil action for injunctive or other appropriate equitable relief in order to protect the peaceable exercise or enjoyment of the right or rights secured. Said civil action shall be brought in the name of the commonwealth and shall be instituted either in the superior court for the county in which the conduct complained of occurred or in the superior court for the county in which the person whose conduct complained of resides or has his principal place of business.
    </text>
</law>