<?xml version="1.0" encoding="utf-8"?>
<law>
    <structure>
        <unit label="part" identifier="1" order_by="1" level="1">Administration Of The Government</unit>
        <unit label="title" identifier="6" order_by="6" level="2">Counties And County Officers</unit>
        <unit label="chapter" identifier="34" order_by="34" level="3">Counties And County Commissioners</unit>
    </structure>
    <section_number>23</section_number>
    <catch_line>Gifts; Use And Disposition</catch_line>
    <order_by>23</order_by>
    <text>
        Any county may receive, hold and manage any gift by devise, bequest or otherwise, to the use or benefit of the county or any activity, institution, organization, board, commission or other public body to the use of which funds of the county are advanced or contributed. Unless otherwise provided by the donor, any money so received or the proceeds of any such gift shall be placed at interest in savings banks or savings departments of trust companies incorporated under the laws of the commonwealth, or in savings departments of national banks, or shall be deposited on paid-up shares and accounts of and in cooperative banks, or shall be used to purchase share accounts of federal savings and loan associations located in the commonwealth, or invested in securities which are legal investments for savings banks. The county treasurer shall be the custodian of such fund and securities, and shall invest and reinvest the same, and expend therefrom moneys as directed by the county commissioners.
    </text>
</law>