<?xml version="1.0" encoding="utf-8"?>
<law>
    <structure>
        <unit label="part" identifier="1" order_by="1" level="1">Administration Of The Government</unit>
        <unit label="title" identifier="8" order_by="8" level="2">Elections</unit>
        <unit label="chapter" identifier="53" order_by="53" level="3">Nominations, Questions To Be Submitted To The Voters, Primaries And Caucuses</unit>
    </structure>
    <section_number>77</section_number>
    <catch_line>Balloting; Use Of Voting Lists</catch_line>
    <order_by>77</order_by>
    <text>
        In balloting, the voting lists furnished under section sixty-two of chapter fifty-one shall be used as check lists, and no persons shall vote or take part in a caucus whose name does not appear upon said lists, unless he presents to the presiding officer of the caucus the certificate provided for by section fifty-nine of said chapter.
    </text>
</law>