<?xml version="1.0" encoding="utf-8"?>
<law>
    <structure>
        <unit label="part" identifier="1" order_by="1" level="1">Administration Of The Government</unit>
        <unit label="title" identifier="7" order_by="7" level="2">Cities, Towns And Districts</unit>
        <unit label="chapter" identifier="40" order_by="40" level="3">Powers And Duties Of Cities And Towns</unit>
    </structure>
    <section_number>4</section_number>
    <catch_line>Towns; Power To Contract; Purposes</catch_line>
    <order_by>4</order_by>
    <text>
        A city or town may make contracts for the exercise of its corporate powers, on such terms and conditions as are authorized by the town meeting in a town, the town council in a town without a town meeting, the city council in a city with the approval of the mayor or the city council in a Plan D or Plan E city with the approval of the manager, or as otherwise authorized in accordance with a duly adopted charter. A city or town may not contract for any purpose, on any terms, or under any conditions inconsistent with any applicable provision of any general or special law.
    </text>
</law>