<?xml version="1.0" encoding="utf-8"?>
<law>
    <structure>
        <unit label="part" identifier="1" order_by="1" level="1">Administration Of The Government</unit>
        <unit label="title" identifier="2" order_by="2" level="2">Executive And Administrative Officers Of The Commonwealth</unit>
        <unit label="chapter" identifier="6" order_by="6" level="3">The Governor, Lieutenant Governor And Council, Certain Officers Under The Governor And Council, And State Library</unit>
    </structure>
    <section_number>133C</section_number>
    <catch_line>New Construction, Remodeling, Etc. Of Public Buildings Or Properties, Vending Facilities</catch_line>
    <order_by>133C</order_by>
    <text>
        To effectuate further the purposes of this act, when new construction, remodeling, leasing, acquisition or improvement of public buildings or properties with the exception of any building, land, or other real property under the jurisdiction of any state university or state institution of higher learning is authorized, the agency directing such construction, remodeling, leasing, acquisition or improvement, shall, when plans include provisions to dispense food products, make available suitable space and facilities for vending facilities to be operated therein by blind persons licensed by the commission for the blind pursuant to the provisions of this chapter.
    </text>
</law>