<?xml version="1.0" encoding="utf-8"?>
<law>
    <structure>
        <unit label="part" identifier="1" order_by="1" level="1">Administration Of The Government</unit>
        <unit label="title" identifier="20" order_by="20" level="2">Public Safety And Good Order</unit>
        <unit label="chapter" identifier="146" order_by="146" level="3">Inspection Of Boilers, Air Tanks, Etc. Licenses Of Engineers, Firemen, And Operators Of Hoisting Machinery</unit>
    </structure>
    <section_number>65</section_number>
    <catch_line>Operators Of Hoisting Machinery; Licenses; Application; Examination</catch_line>
    <order_by>65</order_by>
    <text>
        Whoever desires to act as an operator of hoisting machinery shall apply to the department for a license. If the criteria for licensure established by the commissioner pursuant to section fifty-three are met by the applicant, such applicant shall be required to pass a written or practical examination, or both, in accordance with the standards set in regulations promulgated under the provisions of said section fifty-three. Any operator of hoisting machinery whose license is revoked, and any person who is penalized under the provisions of section fifty-four A, shall be required to pass both a written and practical examination before he may be issued a subsequent license. The passing of the applicable examination shall entitle the applicant to a license to operate hoisting machinery in the category or categories for which he has applied and been examined. Each license issued shall contain a photograph of the licensee.
    </text>
</law>