<?xml version="1.0" encoding="utf-8"?>
<law>
    <structure>
        <unit label="part" identifier="1" order_by="1" level="1">Administration Of The Government</unit>
        <unit label="title" identifier="7" order_by="7" level="2">Cities, Towns And Districts</unit>
        <unit label="chapter" identifier="44" order_by="44" level="3">Municipal Finance</unit>
    </structure>
    <section_number>24A</section_number>
    <catch_line>Bearer Instruments</catch_line>
    <order_by>24A</order_by>
    <text>
        City, town and district notes may be made payable to “bearer”, and when so issued section twenty-four may be construed by the director as being properly complied with in so far as it relates to the proper filling in of any space provided for the name of the purchaser or registered holder of the loan, and the director may certify such notes; provided that before certification there shall be filed with the director by the city, town or district treasurer, as the case may be, the name of the purchaser of such loan.
    </text>
</law>