<?xml version="1.0" encoding="utf-8"?>
<law>
    <structure>
        <unit label="part" identifier="3" order_by="3" level="1">Courts, Judicial Officers And Proceedings In Civil Cases</unit>
        <unit label="title" identifier="4" order_by="4" level="2">Certain Writs And Proceedings In Special Cases</unit>
        <unit label="chapter" identifier="255D" order_by="255D" level="3">Retail Installment Sales And Services</unit>
    </structure>
    <section_number>20</section_number>
    <catch_line>Delinquency And Collection Charge; Dishonored Check Charge</catch_line>
    <order_by>20</order_by>
    <text>
        The holder of a retail installment sale agreement may, if the agreement so provides, collect a delinquency and collection charge on each installment in default for a period of not less than fifteen days in an amount not in excess of five percent of each installment or five dollars, whichever is less, and assess and collect a charge, not to exceed ten dollars, for any check, draft or order for the payment of money submitted in accordance with said agreement which is returned unpaid or not honored by a bank or other depository.
    </text>
</law>