<?xml version="1.0" encoding="utf-8"?>
<law>
    <structure>
        <unit label="part" identifier="1" order_by="1" level="1">Administration Of The Government</unit>
        <unit label="title" identifier="12" order_by="12" level="2">Education</unit>
        <unit label="chapter" identifier="74" order_by="74" level="3">Vocational Education</unit>
    </structure>
    <section_number>2B</section_number>
    <catch_line>Construction Program Students; Low Income Housing</catch_line>
    <order_by>2B</order_by>
    <text>
        Notwithstanding any general or special law to the contrary, a city or town may provide for the construction of one and two family dwellings for persons of low income, by students in vocational-technical schools enrolled in construction programs. 
No such construction shall be undertaken without the prior approval of the division of occupational education and in a city with the prior approval of the mayor and council or in a town with the prior approval of the town council, or if there is no town council, with the approval of the town meeting and board of selectmen.
    </text>
</law>