<?xml version="1.0" encoding="utf-8"?>
<law>
    <structure>
        <unit label="part" identifier="1" order_by="1" level="1">Administration Of The Government</unit>
        <unit label="title" identifier="19" order_by="19" level="2">Agriculture And Conservation</unit>
        <unit label="chapter" identifier="132A" order_by="132A" level="3">State Recreation Areas Outside Of The Metropolitan Parks District</unit>
    </structure>
    <section_number>7G</section_number>
    <catch_line>Payment To Owner</catch_line>
    <order_by>7G</order_by>
    <text>
        If within 2 years after the sale the owner claims the property and proves ownership to the satisfaction of the division, the amount of the unclaimed money or the proceeds of the sale of the property, after deducting reasonable expenses, shall be paid to him by the state treasurer out of the special account, without appropriation.
    </text>
</law>