<?xml version="1.0" encoding="utf-8"?>
<law>
    <structure>
        <unit label="part" identifier="1" order_by="1" level="1">Administration Of The Government</unit>
        <unit label="title" identifier="21" order_by="21" level="2">Labor And Industries</unit>
        <unit label="chapter" identifier="149" order_by="149" level="3">Labor And Industries</unit>
    </structure>
    <section_number>121</section_number>
    <catch_line>Nonapplicability Of Statutes Relating To Emery And Buffing Machinery</catch_line>
    <order_by>121</order_by>
    <text>
        The two preceding sections shall not apply to grinding machines upon which water is used at the point of grinding contact, nor to solid emery wheels used in sawmills or in planing mills or in other woodworking establishments, nor to any emery wheel six inches or less in diameter used in establishments where the principal business is not emery wheel grinding.
    </text>
</law>