<?xml version="1.0" encoding="utf-8"?>
<law>
    <structure>
        <unit label="part" identifier="1" order_by="1" level="1">Administration Of The Government</unit>
        <unit label="title" identifier="22" order_by="22" level="2">Corporations</unit>
        <unit label="chapter" identifier="175" order_by="175" level="3">Insurance</unit>
    </structure>
    <section_number>19V</section_number>
    <catch_line>Transactions Entered Into By Mutual Insurers For Purpose Of Avoiding  Total Gross Investment Income Earned Excise   </catch_line>
    <order_by>19V</order_by>
    <text>
        Any transaction entered into by a mutual insurer, either during or after the reorganization process authorized by sections 19F to 19W, inclusive, a principal purpose of which is to avoid the total gross investment income earned excise imposed by section 22A of chapter 63 or the investment privilege excise imposed by section 22B of said chapter 63 shall be disregarded by the department of revenue for purposes of computing said excise for the reorganized insurer. The department of revenue, in consultation with the division of insurance, shall promulgate rules and regulations necessary to implement the provisions of this section, and may consult with representatives of the insurance industry and practitioners.
    </text>
</law>