<?xml version="1.0" encoding="utf-8"?>
<law>
    <structure>
        <unit label="part" identifier="1" order_by="1" level="1">Administration Of The Government</unit>
        <unit label="title" identifier="22" order_by="22" level="2">Corporations</unit>
        <unit label="chapter" identifier="175E" order_by="175E" level="3">Regulation Of Rates For Motor Vehicle Insurance</unit>
    </structure>
    <section_number>13</section_number>
    <catch_line>Enforcement Of Orders; Jurisdiction; Review</catch_line>
    <order_by>13</order_by>
    <text>
        The supreme judicial court for the county of Suffolk shall have jurisdiction in equity upon the petition of the commissioner and upon a summary hearing to enforce all lawful orders of the commissioner. Any person aggrieved by any action of the commissioner under this chapter may, within twenty days of the action in question, file a petition for review in the supreme judicial court for the county of Suffolk.
    </text>
</law>