<?xml version="1.0" encoding="utf-8"?>
<law>
    <structure>
        <unit label="part" identifier="1" order_by="1" level="1">Administration Of The Government</unit>
        <unit label="title" identifier="9" order_by="9" level="2">Taxation</unit>
        <unit label="chapter" identifier="62C" order_by="62C" level="3">Administrative Provisions Relative To State Taxation</unit>
    </structure>
    <section_number>45B</section_number>
    <catch_line>Declarations Of Estimated Tax And Estimated Tax Payments; Filing Or Payment Made To Bank Designated As Depositary And Fiscal Agent</catch_line>
    <order_by>45B</order_by>
    <text>
        With respect to declarations of estimated tax and estimated tax payments required under the provisions of chapters sixty-two B and sixty-three B, the commissioner may, by regulation, provide that such declarations be filed and estimated tax payments be made to a bank designated as a depositary and fiscal agent under section forty-five. The use of a bank for this purpose shall not be considered a violation of the provisions of section twenty-one; provided, however, that all employees of said bank having access to declarations or documents to which section twenty-one is applicable shall be subject to the provisions of said section twenty-one, including the penalties for their violation under subsection (c) of said section twenty-one.
    </text>
</law>