<?xml version="1.0" encoding="utf-8"?>
<law>
    <structure>
        <unit label="part" identifier="3" order_by="3" level="1">Courts, Judicial Officers And Proceedings In Civil Cases</unit>
        <unit label="title" identifier="1" order_by="1" level="2">Courts And Judicial Officers</unit>
        <unit label="chapter" identifier="218" order_by="218" level="3">District Courts</unit>
    </structure>
    <section_number>25</section_number>
    <catch_line>Costs; Discretion Of Court</catch_line>
    <order_by>25</order_by>
    <text>
        In any civil action begun by summons and complaint which might have been begun under the procedure, the rules for the procedure may provide, or the court may by special order direct, that the cost to be recovered by the plaintiff, if he prevails, shall be eliminated in whole or in part.
    </text>
</law>