<?xml version="1.0" encoding="utf-8"?>
<law>
    <structure>
        <unit label="part" identifier="3" order_by="3" level="1">Courts, Judicial Officers And Proceedings In Civil Cases</unit>
        <unit label="title" identifier="1" order_by="1" level="2">Courts And Judicial Officers</unit>
        <unit label="chapter" identifier="217" order_by="217" level="3">Judges And Registers Of Probate And Insolvency</unit>
    </structure>
    <section_number>35B</section_number>
    <catch_line>Assistant Registers, Judicial Case Managers And Administrative Deputy Assistants; Salaries</catch_line>
    <order_by>35B</order_by>
    <text>
        The salaries of first assistant registers, judicial case managers and administrative deputy assistants of the probate and family court department shall be 83.5 per cent of the salary of the registers pursuant to section 35A and shall be paid by the commonwealth. The salaries of assistant registers and assistant judicial case managers shall be 77 per cent of the salary of the registers of the department pursuant to section 35A and shall be paid, subject to appropriation, by the commonwealth. 
The first assistant registers, assistant registers, judicial case managers and assistant judicial case managers of probate shall devote their entire time during business hours to their respective duties and shall not directly or indirectly engage in the practice of law.
    </text>
</law>