<?xml version="1.0" encoding="utf-8"?>
<law>
    <structure>
        <unit label="part" identifier="1" order_by="1" level="1">Administration Of The Government</unit>
        <unit label="title" identifier="15" order_by="15" level="2">Regulation Of Trade</unit>
        <unit label="chapter" identifier="94" order_by="94" level="3">Inspection And Sale Of Food, Drugs And Various Articles</unit>
    </structure>
    <section_number>55</section_number>
    <catch_line>Fraud In Sale Of Oleomargarine</catch_line>
    <order_by>55</order_by>
    <text>
        Whoever exposes for sale oleomargarine which is not marked and distinguished by all the marks, words and stamps required by section forty-nine, or whoever does not have upon the exposed contents of each opened tub, package or parcel of oleomargarine a conspicuous placard with the word “oleomargarine” or “margarine” printed thereon in plain, uncondensed gothic letters, not less than one inch long, or whoever himself or by his agent sells or offers for sale any oleomargarine to any person who asks or sends for butter, shall be punished by a fine of one hundred dollars.
    </text>
</law>