<?xml version="1.0" encoding="utf-8"?>
<law>
    <structure>
        <unit label="part" identifier="1" order_by="1" level="1">Administration Of The Government</unit>
        <unit label="title" identifier="18" order_by="18" level="2">Prisons, Imprisonment, Paroles And Pardons</unit>
        <unit label="chapter" identifier="124" order_by="124" level="3">Powers And Duties Of The Department Of Correction</unit>
    </structure>
    <section_number>2</section_number>
    <catch_line>Deputy Commissioners; Duties</catch_line>
    <order_by>2</order_by>
    <text>
        Subject to the supervision and control of the commissioner, the deputy commissioner for institutional services shall be responsible for planning and directing the efficient administration of each correctional institution of the commonwealth by the officers and employees of the institution. 
Subject to the supervision and control of the commissioner, the deputy commissioner for classification and treatment shall be responsible for planning and directing the rehabilitation services of all the correctional institutions of the commonwealth, including the classification, medical, educational, industrial, vocational and recreational programs of each such institution. 
Subject to the supervision and control of the commissioner, the deputy commissioner for personnel and training shall be responsible for planning and directing departmental procedures for the appointment, assignment, transfer, training, supervision, discipline and compensation of officers and employees of the department and the correctional institutions of the commonwealth. 
Subject to the supervision and control of the commissioner, the deputy commissioner for community services shall be responsible for planning and directing community programs and services provided to committed offenders. 
Each of the said deputy commissioners shall perform such other duties as may be assigned to him from time to time by the commissioner.
    </text>
</law>