<?xml version="1.0" encoding="utf-8"?>
<law>
    <structure>
        <unit label="part" identifier="2" order_by="2" level="1">Real And Personal Property And Domestic Relations</unit>
        <unit label="title" identifier="2" order_by="2" level="2">Descent And Distribution, Wills, Estates Of Deceased Persons And Absentees, Guardianship, Conservatorship And Trusts</unit>
        <unit label="chapter" identifier="203" order_by="203" level="3">Trusts</unit>
    </structure>
    <section_number>25A</section_number>
    <catch_line>Investment Of Funds</catch_line>
    <order_by>25A</order_by>
    <text>
        [ Text of section effective until March 31, 2012. Repealed by 2008, 521, Sec. 27. See 2008, 521, Sec. 44 as amended by 2010, 409, Sec. 23 and 2011, 224.]  The trustee under a will or other instrument may, if the trust does not otherwise provide, invest the income or principal of the trust fund in policies of life or endowment insurance or annuity contracts, issued by a life insurance company duly authorized to transact business in the commonwealth pursuant to chapter one hundred and seventy-five, on the life of any beneficiary of the trust or on the life of any person in whose life such beneficiary has an insurable interest.
    </text>
</law>