<?xml version="1.0" encoding="utf-8"?>
<law>
    <structure>
        <unit label="part" identifier="1" order_by="1" level="1">Administration Of The Government</unit>
        <unit label="title" identifier="2" order_by="2" level="2">Executive And Administrative Officers Of The Commonwealth</unit>
        <unit label="chapter" identifier="23G" order_by="23G" level="3">The Massachusetts Development Finance Agency</unit>
    </structure>
    <section_number>36</section_number>
    <catch_line>Interests In Land, Mortgages, Liens And Security Interests; Transfer Upon Termination Of Agency</catch_line>
    <order_by>36</order_by>
    <text>
        Upon termination of the Agency’s existence, title to all lands or any interest therein, which immediately prior to said termination, is held by the Agency, and all mortgage and other titles, liens upon and security interests therein so held by the Agency in or upon lands or interests therein theretofore disposed of by the Agency, shall be, without further action be transferred to and shall be vested in the commonwealth and shall be under the control of the executive office for administration and finance. The secretary of administration and finance is hereby authorized to hold, protect, maintain, and use such lands, or any interest therein, as he deems necessary or desirable to facilitate disposition of such lands or any interest therein, and to dispose of such lands, or any interest therein, by sale, lease or otherwise. The proceeds of any disposition of such lands, or any interest therein, shall be paid into the treasury of the commonwealth and shall be used solely toward meeting the debt service obligations of the General Fund.
    </text>
</law>