<?xml version="1.0" encoding="utf-8"?>
<law>
    <structure>
        <unit label="part" identifier="1" order_by="1" level="1">Administration Of The Government</unit>
        <unit label="title" identifier="5" order_by="5" level="2">Militia</unit>
        <unit label="chapter" identifier="33" order_by="33" level="3">Militia</unit>
    </structure>
    <section_number>70</section_number>
    <catch_line>Courts Of Inquiry; Membership; Duties</catch_line>
    <order_by>70</order_by>
    <text>
        Courts of inquiry, to consist of from one to three officers of at least equal grade with the officer, or with the senior officer if there be more than one, in regard to whom the court is convened, may be convened by the commander-in-chief or by such commanding officers authorized thereto by the commander-in-chief in orders to examine into the nature of any transaction of or accusation or imputation against any officer.
    </text>
</law>